dictionary/__init__.py
dictionary/dictionary.py
berdan_akyurek_dictionary-2.0.0.dist-info/METADATA
berdan_akyurek_dictionary-2.0.0.dist-info/WHEEL
berdan_akyurek_dictionary-2.0.0.dist-info/top_level.txt
berdan_akyurek_dictionary-2.0.0.dist-info/RECORD
