Metadata-Version: 2.1
Name: berdan-akyurek-dictionary
Version: 2.0.0
Summary: UNKNOWN
Author: Berdan Akyürek
License: UNKNOWN
Platform: UNKNOWN
Requires-Python: >=3.8
Requires-Dist: requests (>=2.23.0)
